anishot/__init__.py
anishot/__main__.py
anishot-0.1.0.dist-info/METADATA
anishot-0.1.0.dist-info/RECORD
anishot-0.1.0.dist-info/WHEEL
anishot-0.1.0.dist-info/entry_points.txt
anishot-0.1.0.dist-info/pbr.json
anishot-0.1.0.dist-info/top_level.txt
