Metadata-Version: 2.1
Name: anishot
Version: 0.1.0
Summary: Animate a long screenshot
Home-page: https://github.com/sourcerer-io/anishot
Author: sourcerer-io
Author-email: sergey@sourcerer.io
License: UNKNOWN
Platform: UNKNOWN
Classifier: Development Status :: 5 - Production/Stable
Classifier: Intended Audience :: Information Technology
Classifier: License :: OSI Approved :: MIT License
Classifier: Operating System :: POSIX
Classifier: Programming Language :: Python
Classifier: Programming Language :: Python :: 2
Classifier: Programming Language :: Python :: 2.7
Classifier: Programming Language :: Python :: 3
Classifier: Programming Language :: Python :: 3.4
Classifier: Programming Language :: Python :: 3.5
Classifier: Programming Language :: Python :: 3.6
Requires: pbd
Provides-Extra: devel
Requires-Dist: absl-py
Requires-Dist: imageio
Requires-Dist: Pillow
Provides-Extra: devel
Requires-Dist: pbr; extra == 'devel'
